setup.py
Carhome/__init__.py
Carhome/CarH/__init__.py
Carhome/CarH/CarH/CPProxyPool.py
Carhome/CarH/CarH/ProxyConfig.py
Carhome/CarH/CarH/Utils.py
Carhome/CarH/CarH/__init__.py
Carhome/CarH/CarH/deal_txt.py
Carhome/CarH/CarH/items.py
Carhome/CarH/CarH/middlewares.py
Carhome/CarH/CarH/pipelines.py
Carhome/CarH/CarH/request_test.py
Carhome/CarH/CarH/settings.py
Carhome/CarH/CarH/spiders/__init__.py
Carhome/CarH/CarH/spiders/autohome.py
MYframe01.egg-info/PKG-INFO
MYframe01.egg-info/SOURCES.txt
MYframe01.egg-info/dependency_links.txt
MYframe01.egg-info/top_level.txt