Metadata-Version: 2.1
Name: MYframe01
Version: 0.3
Summary: TEST PROJECT
Home-page: https://github.com/PhilRolins/MYframe/tree/master
Author: CPCPL
Author-email: 206006798@qq.com
Keywords: LLLLL
Classifier: Programming Language :: Python :: 3
Classifier: License :: OSI Approved :: MIT License
Classifier: Operating System :: OS Independent
